LICENSE
README.md
setup.cfg
setup.py
experiments/__init__.py
experiments/attack/__init__.py
experiments/attack/attack_experiments.py
experiments/cascading/__init__.py
experiments/cascading/sim_cascading.py
experiments/defense/__init__.py
experiments/defense/defense_experiments.py
experiments/diffusion/__init__.py
experiments/diffusion/sim_diffusion.py
experiments/robustness/__init__.py
experiments/robustness/approximation_experiments.py
experiments/robustness/scalability_experiments.py
graph_tiger/__init__.py
graph_tiger/attacks.py
graph_tiger/cascading.py
graph_tiger/defenses.py
graph_tiger/diffusion.py
graph_tiger/graphs.py
graph_tiger/measures.py
graph_tiger/simulations.py
graph_tiger/utils.py
graph_tiger.egg-info/PKG-INFO
graph_tiger.egg-info/SOURCES.txt
graph_tiger.egg-info/dependency_links.txt
graph_tiger.egg-info/top_level.txt
tests/__init__.py
tests/test_attacks.py
tests/test_defenses.py
tests/test_measures.py
tests/test_simulations.py
tests/test_visualizations.py